tacitus/__init__.py
tacitus/_version.py
tacitus/tacitus.py
tacitus_notes-0.3.1.dist-info/LICENSE
tacitus_notes-0.3.1.dist-info/METADATA
tacitus_notes-0.3.1.dist-info/WHEEL
tacitus_notes-0.3.1.dist-info/entry_points.txt
tacitus_notes-0.3.1.dist-info/top_level.txt
tacitus_notes-0.3.1.dist-info/RECORD
