Metadata-Version: 2.1
Name: tacitus-notes
Version: 0.3.1
Summary: Generate release notes from git history, using markdown syntax.
Home-page: https://github.com/kopsha/tacitus-notes
Author: Florin Ciurcanu
Author-email: florin.ciurcanu@gmail.com
License: BSD 2-Clause License
Keywords: automatic release notes,release notes,markdown,git scraping
Classifier: License :: OSI Approved :: BSD License
Classifier: Programming Language :: Python :: 3
Classifier: Operating System :: OS Independent
Requires-Python: >=3.7
License-File: LICENSE
